NewsBetter/__init__.py
NewsBetter/__main__.py
NewsBetter-1.0.4.dist-info/AUTHORS
NewsBetter-1.0.4.dist-info/LICENSE
NewsBetter-1.0.4.dist-info/METADATA
NewsBetter-1.0.4.dist-info/WHEEL
NewsBetter-1.0.4.dist-info/entry_points.txt
NewsBetter-1.0.4.dist-info/top_level.txt
NewsBetter-1.0.4.dist-info/RECORD
